{
  "culture": "Nigerian",
  "language": "English",
  "topic": null,
  "dimensions": [
    "population_rank",
    "population_distribution",
    "land_area_percentage",
    "main_regions",
    "ethnicity",
    "official_languages",
    "widely_spoken_languages",
    "famous_rivers",
    "climate_geography",
    "national_holidays",
    "religious_holidays",
    "cultural_holidays",
    "festival_origins",
    "festival_celebrations",
    "festival_symbols",
    "vehicle_movement_rules",
    "traffic_signs_and_signals",
    "pedestrian_rules",
    "motor_vehicle_driving_rules",
    "parking_regulations",
    "date_order",
    "date_separator",
    "year_format",
    "month_representation",
    "zero_padding",
    "natural_language_date",
    "calendar_system",
    "measurement_system",
    "unit_localization",
    "financial_regulation_structure",
    "financial_market_type",
    "financial_entity_types",
    "financial_access_licensing",
    "financial_conduct_compliance",
    "financial_capital_risk",
    "monetary_payment_system",
    "fintech_regulation",
    "financial_tax_accounting",
    "financial_international_alignment",
    "financial_stability_resolution",
    "payment_habits",
    "travel_habits",
    "bathing_habits",
    "pet_raising_habits",
    "social_media_usage",
    "marriage_customs",
    "eating_habits",
    "attitudes_lifecycle",
    "traditional_vs_modern_medicine",
    "educational_practices",
    "teacher_student_relationship",
    "academic_major_selection",
    "career_choices",
    "diaspora_festive_activities",
    "traditional_music_and_dance",
    "contemporary_art",
    "basic_etiquette",
    "naming_convention",
    "name_origin",
    "name_significance",
    "punctuality_visiting",
    "shoe_etiquette",
    "guest_hospitality",
    "host_gift_customs",
    "seating_etiquette",
    "serving_etiquette",
    "leaving_food_etiquette",
    "salt_etiquette",
    "meal_compliments",
    "right_hand_eating",
    "alcohol_etiquette",
    "pork_dietary_norms",
    "gift_giving_gesture",
    "gifts_for_children",
    "gift_opening_norms",
    "general_greeting_principles",
    "male_male_greetings",
    "female_female_greetings",
    "male_female_greetings",
    "business_appointment_scheduling",
    "business_dress_code",
    "business_card_exchange",
    "business_network_building",
    "seniority_in_business",
    "business_familiarity",
    "business_socialization",
    "meeting_duration",
    "open_door_policy",
    "business_meeting_interruptions",
    "deference_to_seniority",
    "negotiation_style",
    "business_decision_making",
    "business_bartering",
    "private_business_meetings",
    "confrontation_avoidance_business",
    "business_meeting_followup",
    "ongoing_negotiations",
    "verbal_communication_style",
    "indirect_communication",
    "cultural_humour",
    "physical_contact_norms",
    "personal_space_norms",
    "communication_gestures",
    "beckoning_gestures",
    "eye_contact_norms",
    "linguistic_idioms",
    "common_sayings",
    "proverbs",
    "neologisms_and_abbreviations",
    "communal_living",
    "parental_care_norms",
    "patriarchal_structures",
    "womens_family_roles",
    "household_social_interaction",
    "urban_rural_divide",
    "seniority_and_childhood",
    "male_dominance",
    "gender_social_compliance",
    "gender_and_honour",
    "changing_gender_attitudes",
    "power_distance",
    "collectivism",
    "individualism",
    "achievement_motivation",
    "uncertainty_avoidance",
    "long_term_orientation",
    "cultural_indulgence",
    "religious_beliefs_and_practices",
    "modest_dress_norms",
    "informality_norms",
    "compliment_norms",
    "cultural_acknowledgement",
    "education_as_value",
    "cultural_insults",
    "inappropriate_humor",
    "political_criticism_norms",
    "culturally_sensitive_topics",
    "ethnicity_assumptions",
    "cultural_stereotyping"
  ],
  "completed": [
    "gender_social_compliance",
    "indirect_communication",
    "neologisms_and_abbreviations",
    "linguistic_idioms",
    "male_dominance",
    "national_holidays",
    "ethnicity_assumptions",
    "festival_symbols",
    "date_order",
    "financial_international_alignment",
    "womens_family_roles",
    "official_languages",
    "cultural_stereotyping",
    "household_social_interaction",
    "land_area_percentage",
    "cultural_acknowledgement",
    "cultural_indulgence",
    "compliment_norms",
    "personal_space_norms",
    "leaving_food_etiquette",
    "financial_regulation_structure",
    "marriage_customs",
    "cultural_insults",
    "alcohol_etiquette",
    "traffic_signs_and_signals",
    "private_business_meetings",
    "financial_capital_risk",
    "population_distribution",
    "inappropriate_humor",
    "serving_etiquette",
    "social_media_usage",
    "financial_entity_types",
    "climate_geography",
    "pedestrian_rules",
    "monetary_payment_system",
    "host_gift_customs",
    "shoe_etiquette",
    "zero_padding",
    "traditional_vs_modern_medicine",
    "patriarchal_structures",
    "date_separator",
    "power_distance",
    "verbal_communication_style",
    "business_card_exchange",
    "ongoing_negotiations",
    "deference_to_seniority",
    "month_representation",
    "main_regions",
    "female_female_greetings",
    "modest_dress_norms",
    "traditional_music_and_dance",
    "gifts_for_children",
    "vehicle_movement_rules",
    "calendar_system",
    "business_socialization",
    "business_appointment_scheduling",
    "confrontation_avoidance_business",
    "proverbs",
    "basic_etiquette",
    "culturally_sensitive_topics",
    "business_bartering",
    "open_door_policy",
    "business_decision_making",
    "teacher_student_relationship",
    "diaspora_festive_activities",
    "communal_living",
    "changing_gender_attitudes",
    "bathing_habits",
    "religious_beliefs_and_practices",
    "general_greeting_principles",
    "population_rank",
    "career_choices",
    "measurement_system",
    "informality_norms",
    "business_meeting_followup",
    "contemporary_art",
    "name_significance",
    "common_sayings",
    "ethnicity",
    "achievement_motivation",
    "communication_gestures",
    "cultural_humour",
    "academic_major_selection",
    "business_dress_code",
    "festival_origins",
    "physical_contact_norms",
    "famous_rivers",
    "year_format",
    "widely_spoken_languages",
    "naming_convention",
    "educational_practices",
    "name_origin",
    "male_male_greetings",
    "financial_conduct_compliance",
    "education_as_value",
    "eating_habits",
    "seating_etiquette",
    "pet_raising_habits",
    "long_term_orientation",
    "financial_market_type",
    "unit_localization",
    "salt_etiquette",
    "gender_and_honour",
    "punctuality_visiting",
    "seniority_and_childhood",
    "festival_celebrations",
    "natural_language_date",
    "business_familiarity",
    "attitudes_lifecycle",
    "financial_access_licensing",
    "business_network_building",
    "motor_vehicle_driving_rules",
    "parking_regulations",
    "pork_dietary_norms",
    "gift_opening_norms",
    "guest_hospitality",
    "parental_care_norms",
    "financial_stability_resolution",
    "seniority_in_business",
    "financial_tax_accounting",
    "fintech_regulation",
    "cultural_holidays",
    "right_hand_eating",
    "meeting_duration",
    "negotiation_style",
    "male_female_greetings",
    "individualism",
    "collectivism",
    "beckoning_gestures",
    "travel_habits",
    "political_criticism_norms",
    "urban_rural_divide",
    "uncertainty_avoidance",
    "meal_compliments",
    "eye_contact_norms",
    "gift_giving_gesture",
    "payment_habits",
    "business_meeting_interruptions",
    "religious_holidays"
  ],
  "failed": [],
  "started_at": "2026-03-10T03:31:13.123720+00:00",
  "last_updated": "2026-03-10T18:57:12.138681+00:00"
}